{
  "$schema": "https://schema.management.azure.com/schemas/2015-01-01/deploymentTemplate.json#",
  "contentVersion": "1.0.0.0",
  "parameters": {
    "buildingBlocksRootUri": {
      "type": "string",
      "defaultValue": "https://raw.githubusercontent.com/mspnp/template-building-blocks/master/",
      "metadata": {
        "description": "Root path for templates"
      }
    },
    "parameterRootUri": {
      "type": "string",
      "defaultValue": "https://raw.githubusercontent.com/mspnp/reference-architectures/master/guidance-hybrid-network-secure-vnet-dmz/parameters/",
      "metadata": {
        "decription": "Root path for parameters"
      }
    },
    "adminPassword": {
      "type": "securestring",
      "defaultValue": null
    },
    "sshPublicKey": {
      "type": "securestring",
      "defaultValue": null
    }
  },
  "variables": {
    "templates": {
      "deployment": {
        "multiVMs": "[concat(parameters('buildingBlocksRootUri'), 'templates/buildingBlocks/multi-vm-n-nic-m-storage/azuredeploy.json')]",
        "dmz": "[concat(parameters('buildingBlocksRootUri'), 'templates/buildingBlocks/dmz/azuredeploy.json')]",
        "networkSecurityGroups": "[concat(parameters('buildingBlocksRootUri'), 'templates/buildingBlocks/networkSecurityGroups/azuredeploy.json')]"
      },
      "parameter": {
        "mgmtSubnetVMs": "[concat(parameters('parameterRootUri'), 'virtualMachines-mgmt-subnet.parameters.json')]",
        "dmz": "[concat(parameters('parameterRootUri'), 'dmz.parameters.json')]",
        "internetDmz": "[concat(parameters('parameterRootUri'), 'internet-dmz.parameters.json')]",
        "networkSecurityGroups": "[concat(parameters('parameterRootUri'), 'networkSecurityGroups.parameters.json')]"
      }
    },
    "parametersTemplate": "[concat(parameters('parameterRootUri'), '../parameterLink-resolver.json')]",
    "mgmtParametersDeploymentName": "mgmt-params-Deployment",
    "dmzParametersDeploymentName": "dmz-params-Deployment",
    "internetDmzParametersDeploymentName": "internetDmz-params-Deployment"
  },
  "resources": [
    {
      "type": "Microsoft.Resources/deployments",
      "apiVersion": "2015-01-01",
      "name": "[variables('mgmtParametersDeploymentName')]",
      "properties": {
        "mode": "Incremental",
        "templateLink": {
          "uri": "[variables('parametersTemplate')]"
        },
        "parametersLink": {
          "uri": "[variables('templates').parameter.mgmtSubnetVMs]"
        }
      }
    },
    {
      "type": "Microsoft.Resources/deployments",
      "apiVersion": "2015-01-01",
      "name": "ra-mgmt-vms-deployment",
      "dependsOn": [
        "[variables('mgmtParametersDeploymentName')]"
      ],
      "properties": {
        "mode": "Incremental",
        "templateLink": {
          "uri": "[variables('templates').deployment.multiVMs]"
        },
        "parameters": {
          "virtualMachinesSettings": {
            "value": "[reference(variables('mgmtParametersDeploymentName')).outputs.virtualMachinesSettings.value]"
          },
          "virtualNetworkSettings": {
            "value": "[reference(variables('mgmtParametersDeploymentName')).outputs.virtualNetworkSettings.value]"
          },
          "buildingBlockSettings": {
            "value": "[reference(variables('mgmtParametersDeploymentName')).outputs.buildingBlockSettings.value]"
          },
          "protectedSettings": {
            "value": {
              "adminPassword": "[parameters('adminPassword')]",
              "sshPublicKey": "[parameters('sshPublicKey')]"
            }
          }
        }
      }
    },
    {
      "type": "Microsoft.Resources/deployments",
      "apiVersion": "2015-01-01",
      "name": "[variables('dmzParametersDeploymentName')]",
      "properties": {
        "mode": "Incremental",
        "templateLink": {
          "uri": "[variables('parametersTemplate')]"
        },
        "parametersLink": {
          "uri": "[variables('templates').parameter.dmz]"
        }
      }
    },
    {
      "type": "Microsoft.Resources/deployments",
      "apiVersion": "2015-01-01",
      "name": "ra-dmz-deployment",
      "dependsOn": [
        "[variables('dmzParametersDeploymentName')]"
      ],
      "properties": {
        "mode": "Incremental",
        "templateLink": {
          "uri": "[variables('templates').deployment.dmz]"
        },
        "parameters": {
          "dmzSettings": {
            "value": "[reference(variables('dmzParametersDeploymentName')).outputs.dmzSettings.value]"
          },
          "virtualNetworkSettings": {
            "value": "[reference(variables('dmzParametersDeploymentName')).outputs.virtualNetworkSettings.value]"
          },
          "protectedSettings": {
            "value": {
              "adminPassword": "[parameters('adminPassword')]",
              "sshPublicKey": "[parameters('sshPublicKey')]"
            }
          }
        }
      }
    },
    {
      "type": "Microsoft.Resources/deployments",
      "apiVersion": "2015-01-01",
      "name": "[variables('internetDmzParametersDeploymentName')]",
      "properties": {
        "mode": "Incremental",
        "templateLink": {
          "uri": "[variables('parametersTemplate')]"
        },
        "parametersLink": {
          "uri": "[variables('templates').parameter.internetDmz]"
        }
      }
    },
    {
      "type": "Microsoft.Resources/deployments",
      "apiVersion": "2015-01-01",
      "name": "ra-internet-dmz-deployment",
      "dependsOn": [
        "[variables('internetDmzParametersDeploymentName')]"
      ],
      "properties": {
        "mode": "Incremental",
        "templateLink": {
          "uri": "[variables('templates').deployment.dmz]"
        },
        "parameters": {
          "dmzSettings": {
            "value": "[reference(variables('internetDmzParametersDeploymentName')).outputs.dmzSettings.value]"
          },
          "virtualNetworkSettings": {
            "value": "[reference(variables('internetDmzParametersDeploymentName')).outputs.virtualNetworkSettings.value]"
          },
          "protectedSettings": {
            "value": {
              "adminPassword": "[parameters('adminPassword')]",
              "sshPublicKey": "[parameters('sshPublicKey')]"
            }
          }
        }
      }
    },
    {
      "type": "Microsoft.Resources/deployments",
      "apiVersion": "2015-01-01",
      "name": "ra-nsg-deployment",
      "properties": {
        "mode": "Incremental",
        "templateLink": {
          "uri": "[variables('templates').deployment.networkSecurityGroups]"
        },
        "parametersLink": {
          "uri": "[variables('templates').parameter.networkSecurityGroups]"
        }
      }
    }
  ],
  "outputs": {
  }
}

